[
  {
    "channel_name": "Психолог Вероника Степанова",
    "channel_url": "https://www.youtube.com/@veronikastepanova1978.",
    "video_count": 11,
    "queries": [
      "выгорание",
      "как научиться говорить нет",
      "как перестать всем угождать",
      "как перестать прокрастинировать",
      "как полюбить себя",
      "как справиться с тревогой",
      "личные границы",
      "самосаботаж",
      "синдром самозванца",
      "социофобия",
      "токсичные отношения"
    ],
    "total_views": 14141672,
    "sample_titles": [
      "КАК ЖЕНЩИНЕ НАУЧИТЬСЯ ЛЮБИТЬ СЕБЯ / ПОЛЮБИТЬ СВОЮ ВНЕШНОСТЬ",
      "Как поставить человека на место / Как реагировать на хамство / Как защитить свои границы?",
      "Свобода говорить НЕТ / Как научиться отказывать людям / Пять действенных приемов"
    ]
  },
  {
    "channel_name": "Евгения Стрелецкая",
    "channel_url": "https://www.youtube.com/@strl",
    "video_count": 9,
    "queries": [
      "выгорание",
      "как полюбить себя",
      "как справиться с тревогой",
      "личные границы",
      "синдром самозванца",
      "социофобия"
    ],
    "total_views": 9032541,
    "sample_titles": [
      "How to ACCEPT and LOVE YOURSELF + achieve perfection",
      "Личные границы ч.1: как узнать свои границы. Польза злости. 3 степени близости отношений",
      "Get rid of any anxiety on your own: an overview of the best psychotherapeutic methods"
    ]
  },
  {
    "channel_name": "Правое полушарие Интроверта",
    "channel_url": "https://www.youtube.com/@artforintrovert",
    "video_count": 5,
    "queries": [
      "как научиться говорить нет",
      "как полюбить себя",
      "как справиться с тревогой",
      "личные границы",
      "синдром самозванца"
    ],
    "total_views": 3105602,
    "sample_titles": [
      "Почему вы себя не любите?",
      "Why You Shouldn't Sniff People: Personal Boundaries and How to Deal with Them",
      "How to learn to say \"no\""
    ]
  },
  {
    "channel_name": "Простые Мысли",
    "channel_url": "https://www.youtube.com/@prostiemisli",
    "video_count": 4,
    "queries": [
      "как найти себя",
      "как научиться говорить нет",
      "как перестать прокрастинировать"
    ],
    "total_views": 5411721,
    "sample_titles": [
      "HOW to learn to say NO",
      "ПРОКРАСТИНАЦИЯ. Как не откладывать на потом?",
      "HOW TO FIND YOUR CALLING. The Path to Yourself"
    ]
  },
  {
    "channel_name": "Алексей Ситников",
    "channel_url": "https://www.youtube.com/@AlexeySitnikov",
    "video_count": 4,
    "queries": [
      "выгорание",
      "как найти себя",
      "как научиться говорить нет",
      "токсичные отношения"
    ],
    "total_views": 1589455,
    "sample_titles": [
      "Как ГОВОРИТЬ НЕТ — Техники вежливого ОТКАЗА",
      "В чём смысл ТВОЕЙ жизни? /Как понять себя и найти своё призвание?",
      "Признаки эмоционального выгорания! Что делать если выгорел?"
    ]
  },
  {
    "channel_name": "Седа Каспарова",
    "channel_url": "https://www.youtube.com/@SedaKasparova",
    "video_count": 4,
    "queries": [
      "как перестать прокрастинировать",
      "как полюбить себя",
      "личные границы",
      "синдром самозванца"
    ],
    "total_views": 1419883,
    "sample_titles": [
      "Прими себя такой, какая есть! / Как полюбить себя и осознать свою ценность?",
      "Как вызывать уважение и не казаться грубым? Беспроигрышная стратегия для защиты личных границ!",
      "НАСТОЯЩИЕ причины вашей лени! Как побороть лень и перестать прокрастинировать?"
    ]
  },
  {
    "channel_name": "Антон Махновский",
    "channel_url": "https://www.youtube.com/@Makhnovskii",
    "video_count": 4,
    "queries": [
      "как полюбить себя",
      "личные границы",
      "синдром самозванца",
      "токсичные отношения"
    ],
    "total_views": 713072,
    "sample_titles": [
      "How to increase self-esteem. How to learn to love yourself.",
      "How to know your boundaries and how to defend personal boundaries? I message and I statement.",
      "What is impostor syndrome. How to become self-confident. Shame therapy and healthy self-esteem."
    ]
  },
  {
    "channel_name": "Орхан Мустафаев",
    "channel_url": "https://www.youtube.com/@omustafaev",
    "video_count": 3,
    "queries": [
      "как найти себя",
      "как справиться с тревогой"
    ],
    "total_views": 1010232,
    "sample_titles": [
      "Negative Thoughts, Anxiety, Panic Attacks: How to Cope? | Marina Nakhalova",
      "ЖИВУ НЕ СВОЕЙ ЖИЗНЬЮ: как найти себя, не сравнивать с другими, не откладывать жизнь на потом. Голубь",
      "ПОТЕРЯННОЕ ПОКОЛЕНИЕ: как найти себя и почему мы сталкиваемся с кризисом смыслов? Кривцова"
    ]
  },
  {
    "channel_name": "Андрей Курпатов",
    "channel_url": "https://www.youtube.com/@AndreyKurpatov",
    "video_count": 3,
    "queries": [
      "выгорание",
      "как перестать прокрастинировать",
      "синдром самозванца"
    ],
    "total_views": 685465,
    "sample_titles": [
      "How to Stop Procrastinating and Start Taking Action",
      "Даже лучшие, страдают от синдрома самозванца",
      "Усталость, переутомление, выгорание — в чем причина и что делать?"
    ]
  },
  {
    "channel_name": "Клиника доктора Шурова",
    "channel_url": "https://www.youtube.com/@pervyy_shag",
    "video_count": 3,
    "queries": [
      "как справиться с тревогой",
      "социофобия"
    ],
    "total_views": 639128,
    "sample_titles": [
      "ТРЕВОГА! Как избавиться от тревоги | ТОП 3 причины возникновения и последствия",
      "СОЦИОФОБЫ - КТО ОНИ? Как победить страх общения?",
      "СОЦИОФОБИЯ: причины, признаки, последствия | Как избавиться от ТРЕВОГИ? | Лечение СОЦИОФОБИИ"
    ]
  },
  {
    "channel_name": "Дмитрий Компаниец",
    "channel_url": "https://www.youtube.com/@Kompaniiets",
    "video_count": 3,
    "queries": [
      "как найти себя",
      "самосаботаж",
      "синдром самозванца"
    ],
    "total_views": 611000,
    "sample_titles": [
      "Оставь самосаботаж в прошлом году",
      "Гайд по 5 разным синдромам Самозванца",
      "Лучший способ НАЙТИ СЕБЯ / Техника \"Люди-Маяки\""
    ]
  },
  {
    "channel_name": "Психолог - психотерапевт Дмитрий Мелешко",
    "channel_url": "https://www.youtube.com/@MeleshkoD",
    "video_count": 3,
    "queries": [
      "личные границы",
      "синдром самозванца",
      "токсичные отношения"
    ],
    "total_views": 359264,
    "sample_titles": [
      "Подкаст #8. Личные границы. Как выстраивать и устанавливать",
      "Подкаст #13. Синдром самозванца / Как избавиться и почему возникает",
      "Подкаст №76. Почему мы терпим токсичные отношения / Как распознать высокую толерантность к насилию"
    ]
  },
  {
    "channel_name": "Психология с Анеттой Орловой",
    "channel_url": "https://www.youtube.com/@AnettaOrlova",
    "video_count": 3,
    "queries": [
      "как научиться говорить нет",
      "как справиться с тревогой",
      "синдром самозванца"
    ],
    "total_views": 325497,
    "sample_titles": [
      "How to learn to say no without fear and guilt? The price of adapting",
      "Anxiety. How to cope with anxiety?",
      "Как избавиться от СИНДРОМА САМОЗВАНЦА. Алгоритм действий"
    ]
  },
  {
    "channel_name": "Albert",
    "channel_url": "https://www.youtube.com/@albertt",
    "video_count": 2,
    "queries": [
      "как перестать прокрастинировать",
      "как полюбить себя"
    ],
    "total_views": 1435376,
    "sample_titles": [
      "How to Start Respecting Yourself",
      "How to overcome procrastination"
    ]
  },
  {
    "channel_name": "Александр Некрасов",
    "channel_url": "https://www.youtube.com/@anekrasov",
    "video_count": 2,
    "queries": [
      "как найти себя",
      "самосаботаж"
    ],
    "total_views": 1237287,
    "sample_titles": [
      "Как избавиться от Самосаботажа с помощью Теневой работы",
      "Фридрих Ницше - Как найти себя"
    ]
  },
  {
    "channel_name": "Тренер мотиватор Ирина Ковалева",
    "channel_url": "https://www.youtube.com/@ТренермотиваторИринаКовалева",
    "video_count": 2,
    "queries": [
      "как научиться говорить нет",
      "как справиться с тревогой"
    ],
    "total_views": 869578,
    "sample_titles": [
      "Научиться говорить нет",
      "Как преодолеть постоянную тревогу?"
    ]
  },
  {
    "channel_name": "МАРГУЛАН СЕЙСЕМБАЙ",
    "channel_url": "https://www.youtube.com/@Margulan.Seissembai",
    "video_count": 2,
    "queries": [
      "как научиться говорить нет",
      "как перестать прокрастинировать"
    ],
    "total_views": 847344,
    "sample_titles": [
      "Как правильно отказывать? Как правильно говорить НЕТ",
      "Делай ЭТО и лень, и прокрастинация исчезнут! Иначе твоя жизнь превратиться в Г***О"
    ]
  },
  {
    "channel_name": "Dr. Eric Berg - official Russian channel",
    "channel_url": "https://www.youtube.com/@DrEricBerg",
    "video_count": 2,
    "queries": [
      "как справиться с тревогой"
    ],
    "total_views": 743393,
    "sample_titles": [
      "Как избавиться от тревожности и депрессии🤔",
      "Как бороться с тревожностью и справляться со стрессом"
    ]
  },
  {
    "channel_name": "СПРАВИТЬСЯ ПРОЩЕ",
    "channel_url": "https://www.youtube.com/@handlingbetter",
    "video_count": 2,
    "queries": [
      "выгорание",
      "социальная тревога"
    ],
    "total_views": 599849,
    "sample_titles": [
      "СОЦИАЛЬНАЯ ТРЕВОГА. «Боюсь, что меня осудят». Людные места, телефонные звонки, стыд.",
      "ВЫГОРАНИЕ. Как найти баланс и не разрушить жизнь из-за работы"
    ]
  },
  {
    "channel_name": "Дарья Каризская | Психолог",
    "channel_url": "https://www.youtube.com/@D_Kari",
    "video_count": 2,
    "queries": [
      "социальная тревога"
    ],
    "total_views": 459877,
    "sample_titles": [
      "Как расслабиться и не бояться быть собой: стеснительность, застенчивость, социальная тревожность",
      "Как разговаривать с людьми, если не знаешь, что сказать (социальная тревожность)"
    ]
  },
  {
    "channel_name": "АДА КОНДЭ",
    "channel_url": "https://www.youtube.com/@ada_conde",
    "video_count": 2,
    "queries": [
      "как полюбить себя",
      "самосаботаж"
    ],
    "total_views": 392764,
    "sample_titles": [
      "САМЫЙ ЛУЧШИЙ СПОСОБ НАУЧИТЬСЯ ЛЮБИТЬ СЕБЯ. #Адакофе 50",
      "САМОСАБОТАЖ И СТРАХ РАСПЛАТЫ ЗА СЧАСТЬЕ. #Адакофе 119"
    ]
  },
  {
    "channel_name": "Saywerty",
    "channel_url": "https://www.youtube.com/@saywerty_x",
    "video_count": 2,
    "queries": [
      "как найти себя",
      "как полюбить себя"
    ],
    "total_views": 328922,
    "sample_titles": [
      "Почему ты не любишь себя и как это изменить",
      "ПОЛНЫЙ ГАЙД: КАК НАЙТИ СЕБЯ"
    ]
  },
  {
    "channel_name": "Закрой гештальт",
    "channel_url": "https://www.youtube.com/@zakroygeshtalt",
    "video_count": 2,
    "queries": [
      "как перестать всем угождать",
      "личные границы"
    ],
    "total_views": 227090,
    "sample_titles": [
      "Почему НЕ НУЖНО выставлять ЛИЧНЫЕ ГРАНИЦЫ? Психолог Елена Новоселова",
      "3 ЭТАПА как перестать БЫТЬ УДОБНЫМ для всех"
    ]
  },
  {
    "channel_name": "Твоя Психология | Симохин Никита",
    "channel_url": "https://www.youtube.com/@yourpsy",
    "video_count": 2,
    "queries": [
      "социофобия",
      "токсичные отношения"
    ],
    "total_views": 83828,
    "sample_titles": [
      "Узнай, есть ли у тебя СОЦИОФОБИЯ | Причины, симптомы, лечение",
      "18 Signs of a Dangerous Partner. Signs of a Toxic Relationship"
    ]
  },
  {
    "channel_name": "Психиатрия и психология, клиника Шмиловича Ре-Альт",
    "channel_url": "https://www.youtube.com/@re-alt",
    "video_count": 2,
    "queries": [
      "выгорание",
      "социальная тревога"
    ],
    "total_views": 69976,
    "sample_titles": [
      "Тревога и страх от жизни / Как победить ТРЕВОЖНОЕ РАССТРОЙСТВО личности?",
      "Надоела работа и ничего не хочется? Вы ВЫГОРЕЛИ! / Чем ОПАСНО эмоциональное выгорание?"
    ]
  },
  {
    "channel_name": "mednauka.net",
    "channel_url": "https://www.youtube.com/@MEDNAUKA",
    "video_count": 2,
    "queries": [
      "социальная тревога",
      "социальная тревожность"
    ],
    "total_views": 9644,
    "sample_titles": [
      "Как победить социальную тревожность",
      "Социальная тревожность"
    ]
  },
  {
    "channel_name": "Телеканал «Доктор»",
    "channel_url": "https://www.youtube.com/@doctorchannel",
    "video_count": 1,
    "queries": [
      "как полюбить себя"
    ],
    "total_views": 9096261,
    "sample_titles": [
      "Как полюбить себя? Психолог Михаил ЛАБКОВСКИЙ"
    ]
  },
  {
    "channel_name": "Алексей Шевцов",
    "channel_url": "https://www.youtube.com/@AlexShevstsov",
    "video_count": 1,
    "queries": [
      "как найти себя"
    ],
    "total_views": 1902749,
    "sample_titles": [
      "КАК НАЙТИ СЕБЯ?"
    ]
  },
  {
    "channel_name": "Таблетка Саморазвития",
    "channel_url": "https://www.youtube.com/@improvementpill_ru",
    "video_count": 1,
    "queries": [
      "социофобия"
    ],
    "total_views": 1316823,
    "sample_titles": [
      "Как Избавиться от Социофобии"
    ]
  },
  {
    "channel_name": "ЧД",
    "channel_url": "https://www.youtube.com/@Ch_D",
    "video_count": 1,
    "queries": [
      "синдром самозванца"
    ],
    "total_views": 971485,
    "sample_titles": [
      "Imposter Syndrome І You're Not Who You Seem І ЧД"
    ]
  },
  {
    "channel_name": "амоБлог",
    "channel_url": "https://www.youtube.com/channel/UC03-38aILdlkFAAc8lE6MQg",
    "video_count": 1,
    "queries": [
      "выгорание"
    ],
    "total_views": 629467,
    "sample_titles": [
      "Выгорание у зумеров, бумеров и миллениалов. ЧТО ДЕЛАТЬ? / Амоблог"
    ]
  },
  {
    "channel_name": "ЛОМАЯ КОНЦЕПЦИИ",
    "channel_url": "https://www.youtube.com/@ЛОМАЯКОНЦЕПЦИИ-ы5д",
    "video_count": 1,
    "queries": [
      "как полюбить себя"
    ],
    "total_views": 581533,
    "sample_titles": [
      "ВОТ что произойдёт, если вы поставите себя на первое место - Карл Юнг"
    ]
  },
  {
    "channel_name": "Сама Меньшова",
    "channel_url": "https://www.youtube.com/@samamenshova",
    "video_count": 1,
    "queries": [
      "личные границы"
    ],
    "total_views": 480577,
    "sample_titles": [
      "Personal Boundaries: How to Set Them? Psychologist Tatyana Shakhbazi on the Importance of Saying ..."
    ]
  },
  {
    "channel_name": "Академия Идей",
    "channel_url": "https://www.youtube.com/@akademiaidei",
    "video_count": 1,
    "queries": [
      "самосаботаж"
    ],
    "total_views": 388736,
    "sample_titles": [
      "Self-sabotage, laziness, procrastination. Why do we harm ourselves?"
    ]
  },
  {
    "channel_name": "Институт психологии Smart",
    "channel_url": "https://www.youtube.com/@smart_inc_psy",
    "video_count": 1,
    "queries": [
      "выгорание"
    ],
    "total_views": 334534,
    "sample_titles": [
      "ВЫГОРАНИЕ на работе и в жизни. Почему вы постоянно УСТАЕТЕ? О чём говорят усталость и апатия? Орлова"
    ]
  },
  {
    "channel_name": "Психология | Игропрактика Лила",
    "channel_url": "https://www.youtube.com/@Tuttabene",
    "video_count": 1,
    "queries": [
      "как найти себя"
    ],
    "total_views": 312983,
    "sample_titles": [
      "DO THIS and you will understand your TRUE DESIRES! How can I understand what I REALLY want?"
    ]
  },
  {
    "channel_name": "Доктор Сычев",
    "channel_url": "https://www.youtube.com/@dr_sychev",
    "video_count": 1,
    "queries": [
      "как перестать прокрастинировать"
    ],
    "total_views": 267261,
    "sample_titles": [
      "ADHD and Motivation: How to Stop Procrastinating and Get Things Done"
    ]
  },
  {
    "channel_name": "Марк Бартон",
    "channel_url": "https://www.youtube.com/@Mark_Barton",
    "video_count": 1,
    "queries": [
      "токсичные отношения"
    ],
    "total_views": 243516,
    "sample_titles": [
      "Болезненные, токсичные отношения. Почему вы находитесь в таких отношениях?"
    ]
  },
  {
    "channel_name": "Ель Студия",
    "channel_url": "https://www.youtube.com/@ellofficia1",
    "video_count": 1,
    "queries": [
      "выгорание"
    ],
    "total_views": 233635,
    "sample_titles": [
      "How to Know if You're Burned Out [Psych2go in Russian]"
    ]
  },
  {
    "channel_name": "35 тв",
    "channel_url": "https://www.youtube.com/@35тв",
    "video_count": 1,
    "queries": [
      "как справиться с тревогой"
    ],
    "total_views": 224523,
    "sample_titles": [
      "5 советов от врача-психиатра: как избавиться от тревоги?"
    ]
  },
  {
    "channel_name": "Ирина Хакамада",
    "channel_url": "https://www.youtube.com/@irina.hakamada",
    "video_count": 1,
    "queries": [
      "синдром самозванца"
    ],
    "total_views": 214917,
    "sample_titles": [
      "Синдром самозванца, как избавиться?"
    ]
  },
  {
    "channel_name": "Alexandra Posnova",
    "channel_url": "https://www.youtube.com/@AlexandraPosnova",
    "video_count": 1,
    "queries": [
      "как справиться с тревогой"
    ],
    "total_views": 214400,
    "sample_titles": [
      "Справиться с Тревогой и Стрессом: 10 Способов Самопомощи"
    ]
  },
  {
    "channel_name": "Murad Sultanov",
    "channel_url": "https://www.youtube.com/@muradsultanov7804",
    "video_count": 1,
    "queries": [
      "социофобия"
    ],
    "total_views": 210255,
    "sample_titles": [
      "CОЦИОФОБИЯ – 4 симптома социальной фобии, как определяется диагноз"
    ]
  },
  {
    "channel_name": "Соколовский | Мысли Вслух",
    "channel_url": "https://www.youtube.com/@AlexSokolovskiy",
    "video_count": 1,
    "queries": [
      "как перестать всем угождать"
    ],
    "total_views": 210215,
    "sample_titles": [
      "5 Realizations That Will Free You From the Role of a Convenient Person Forever"
    ]
  },
  {
    "channel_name": "Malyshka Polly",
    "channel_url": "https://www.youtube.com/@polyaam",
    "video_count": 1,
    "queries": [
      "как найти себя"
    ],
    "total_views": 204524,
    "sample_titles": [
      "как найти себя? || 5 советов и практик *это нужно знать*"
    ]
  },
  {
    "channel_name": "Анастасия Истинова",
    "channel_url": "https://www.youtube.com/@istinova",
    "video_count": 1,
    "queries": [
      "как перестать всем угождать"
    ],
    "total_views": 195672,
    "sample_titles": [
      "Как перестать пытаться нравиться всем и понравиться себе:"
    ]
  },
  {
    "channel_name": "Психолог Сахаровская Наталья",
    "channel_url": "https://www.youtube.com/@Natalia_Sakharovskaya",
    "video_count": 1,
    "queries": [
      "как полюбить себя"
    ],
    "total_views": 188110,
    "sample_titles": [
      "КАК ПОЛЮБИТЬ СЕБЯ. ПОЧЕМУ НЕ РАБОТАЮТ СОВЕТЫ \"ПОБАЛУЙ СЕБЯ\". КАК ПОЗАБОТИТЬСЯ О ВНУТРЕННЕМ РЕБЕНКЕ."
    ]
  },
  {
    "channel_name": "Павел Зыгмантович | Доказательная психология",
    "channel_url": "https://www.youtube.com/@pavelzyg",
    "video_count": 1,
    "queries": [
      "самосаботаж"
    ],
    "total_views": 188050,
    "sample_titles": [
      "Self-Sabotage: This Is Why You're Ruining Your Life"
    ]
  },
  {
    "channel_name": "Anna Roudakova",
    "channel_url": "https://www.youtube.com/@anna.roudakova",
    "video_count": 1,
    "queries": [
      "как полюбить себя"
    ],
    "total_views": 176892,
    "sample_titles": [
      "Как по-настоящему полюбить себя"
    ]
  },
  {
    "channel_name": "FreshLife28",
    "channel_url": "https://www.youtube.com/@Freshlife28",
    "video_count": 1,
    "queries": [
      "личные границы"
    ],
    "total_views": 153265,
    "sample_titles": [
      "Personal boundaries - what are personal boundaries and why defend them?"
    ]
  },
  {
    "channel_name": "Ольга Демчук",
    "channel_url": "https://www.youtube.com/@OlgaDemchuk",
    "video_count": 1,
    "queries": [
      "личные границы"
    ],
    "total_views": 152184,
    "sample_titles": [
      "Вебинар \"Личностные границы\". Безграничность, слияние, ограниченность и индивидуальность."
    ]
  },
  {
    "channel_name": "amirkamilla",
    "channel_url": "https://www.youtube.com/@amirkamilla",
    "video_count": 1,
    "queries": [
      "как перестать прокрастинировать"
    ],
    "total_views": 136094,
    "sample_titles": [
      "КАК ПЕРЕСТАТЬ ПРОКРАСТИНИРОВАТЬ И ПОЛЮБИТЬ УЧИТЬСЯ: мои рабочие техники"
    ]
  },
  {
    "channel_name": "Michail Labkovskiy",
    "channel_url": "https://www.youtube.com/@MichailLabkovskiy",
    "video_count": 1,
    "queries": [
      "как перестать всем угождать"
    ],
    "total_views": 129661,
    "sample_titles": [
      "Как перестать всем нравиться: почему мы пытаемся угодить?"
    ]
  },
  {
    "channel_name": "Психолог Иван Лысенко",
    "channel_url": "https://www.youtube.com/@ПсихологИванЛысенко",
    "video_count": 1,
    "queries": [
      "социофобия"
    ],
    "total_views": 126935,
    "sample_titles": [
      "Social phobia how to get rid of Shyness and Fear of people"
    ]
  },
  {
    "channel_name": "Погодин Игорь",
    "channel_url": "https://www.youtube.com/@PogodinIgor",
    "video_count": 1,
    "queries": [
      "социофобия"
    ],
    "total_views": 123888,
    "sample_titles": [
      "ЗАСТЕНЧИВОСТЬ и СОЦИОФОБИЯ. Что с этим делать? | Игорь Погодин"
    ]
  },
  {
    "channel_name": "НаучДок",
    "channel_url": "https://www.youtube.com/@NauchDok",
    "video_count": 1,
    "queries": [
      "синдром самозванца"
    ],
    "total_views": 113165,
    "sample_titles": [
      "How Imposter Syndrome Develops / Svetlana Komissaruk // We Need to Talk"
    ]
  },
  {
    "channel_name": "The Old Man Who Knew Too Much",
    "channel_url": "https://www.youtube.com/@THEOLDMANWHOKNEWTOOMUCH",
    "video_count": 1,
    "queries": [
      "как перестать всем угождать"
    ],
    "total_views": 112553,
    "sample_titles": [
      "Как ПЕРЕСТАТЬ угождать всем и начать расти | Макиавелли"
    ]
  },
  {
    "channel_name": "Psychologist Katya Freud",
    "channel_url": "https://www.youtube.com/@katyafreud",
    "video_count": 1,
    "queries": [
      "токсичные отношения"
    ],
    "total_views": 91153,
    "sample_titles": [
      "9 Signs of Toxic People. Toxic Relationships. Manipulation. Katya Freud"
    ]
  },
  {
    "channel_name": "ПСИХОЛОГИЯ СЧАСТЛИВОЙ ЖИЗНИ",
    "channel_url": "https://www.youtube.com/channel/UCYZpibEJWh-dNXK2BR2gdLg",
    "video_count": 1,
    "queries": [
      "выгорание"
    ],
    "total_views": 85925,
    "sample_titles": [
      "Эмоциональное выгорание | Как бороться с отсутствием желаний - Михаил Лабковский"
    ]
  },
  {
    "channel_name": "РБК Тренды",
    "channel_url": "https://www.youtube.com/@RBCTrends",
    "video_count": 1,
    "queries": [
      "выгорание"
    ],
    "total_views": 74998,
    "sample_titles": [
      "Сгорел на работе: как распознать и победить эмоциональное выгорание"
    ]
  },
  {
    "channel_name": "Vitaliy Buzhan",
    "channel_url": "https://www.youtube.com/@VitaliyBuzhan",
    "video_count": 1,
    "queries": [
      "как перестать прокрастинировать"
    ],
    "total_views": 67271,
    "sample_titles": [
      "Почему прокрастинация разрушает: как перестать прокрастинировать"
    ]
  },
  {
    "channel_name": "Lina Mergold",
    "channel_url": "https://www.youtube.com/@Lina_Mergold",
    "video_count": 1,
    "queries": [
      "как перестать прокрастинировать"
    ],
    "total_views": 64240,
    "sample_titles": [
      "ADHD and Procrastination | How to Stop Being \"Lazier\" | Tips and Reasons"
    ]
  },
  {
    "channel_name": "скорбияк",
    "channel_url": "https://www.youtube.com/@scorbiyach",
    "video_count": 1,
    "queries": [
      "как перестать прокрастинировать"
    ],
    "total_views": 63507,
    "sample_titles": [
      "КАК ПЕРЕСТАТЬ ПРОКРАСТИНИРОВАТЬ | 10 советов, которые РЕАЛЬНО помогают"
    ]
  },
  {
    "channel_name": "ПроБолезни",
    "channel_url": "https://www.youtube.com/@probolezny",
    "video_count": 1,
    "queries": [
      "выгорание"
    ],
    "total_views": 54768,
    "sample_titles": [
      "Эмоциональное выгорание"
    ]
  },
  {
    "channel_name": "Радислав Гандапас - лидерские стратегии",
    "channel_url": "https://www.youtube.com/@RadislavGandapas",
    "video_count": 1,
    "queries": [
      "как научиться говорить нет"
    ],
    "total_views": 50438,
    "sample_titles": [
      "НЕ НУЖНО БЫТЬ УДОБНЫМ. КАК ГОВОРИТЬ НЕТ? | РАДИСЛАВ ГАНДАПАС"
    ]
  },
  {
    "channel_name": "Альберт Сафин",
    "channel_url": "https://www.youtube.com/@seodrum",
    "video_count": 1,
    "queries": [
      "социальная тревога"
    ],
    "total_views": 50132,
    "sample_titles": [
      "Социальная тревожность, застенчивость, стеснительность: что делать? Руководство"
    ]
  },
  {
    "channel_name": "Евгений Дейнеко",
    "channel_url": "https://www.youtube.com/@DeynekoEvgen",
    "video_count": 1,
    "queries": [
      "самосаботаж"
    ],
    "total_views": 49908,
    "sample_titles": [
      "Как за 50 секунд разделаться с самосаботажем и прокрастинацией"
    ]
  },
  {
    "channel_name": "ПСИХОЛОГИЯ СЧАСТЛИВОЙ ЖИЗНИ",
    "channel_url": "https://www.youtube.com/@ПСИХОЛОГИЯСЧАСТЛИВОЙЖИЗНИ",
    "video_count": 1,
    "queries": [
      "как научиться говорить нет"
    ],
    "total_views": 44266,
    "sample_titles": [
      "Как научиться отказывать людям | Почему важно уметь говорить НЕТ - Михаил Лабковский"
    ]
  },
  {
    "channel_name": "Надежда Семененко",
    "channel_url": "https://www.youtube.com/@nsemenenko",
    "video_count": 1,
    "queries": [
      "как перестать всем угождать"
    ],
    "total_views": 42245,
    "sample_titles": [
      "Как перестать угождать людям? 11 признаков угодничества"
    ]
  },
  {
    "channel_name": "Elizaveta Brain",
    "channel_url": "https://www.youtube.com/@elizavetabrain",
    "video_count": 1,
    "queries": [
      "личные границы"
    ],
    "total_views": 33712,
    "sample_titles": [
      "как спокойно выстроить личные границы *с примерами* | после этих техник тебя начнут уважать"
    ]
  },
  {
    "channel_name": "Grehan Animation",
    "channel_url": "https://www.youtube.com/@GrehanAnimation",
    "video_count": 1,
    "queries": [
      "как перестать прокрастинировать"
    ],
    "total_views": 29315,
    "sample_titles": [
      "КАК ИЗБАВИТЬСЯ ОТ ПРОКРАСТИНАЦИИ?"
    ]
  },
  {
    "channel_name": "Сатья ДасТ ответ",
    "channel_url": "https://www.youtube.com/@satyaexpert",
    "video_count": 1,
    "queries": [
      "токсичные отношения"
    ],
    "total_views": 28601,
    "sample_titles": [
      "Сатья. Как не попасть в токсичные отношения"
    ]
  },
  {
    "channel_name": "Зеркало разума",
    "channel_url": "https://www.youtube.com/@zerkalorazuma",
    "video_count": 1,
    "queries": [
      "как перестать всем угождать"
    ],
    "total_views": 25475,
    "sample_titles": [
      "Как перестать всем угождать и вернуть себе свою жизнь (Метод Ницше)."
    ]
  },
  {
    "channel_name": "Евгений Декань",
    "channel_url": "https://www.youtube.com/@individual_dekan",
    "video_count": 1,
    "queries": [
      "самосаботаж"
    ],
    "total_views": 24908,
    "sample_titles": [
      "Самосаботаж. Принимаем и прорабатываем Саботажника. Упражнение эффект уже с первой практики."
    ]
  },
  {
    "channel_name": "Psych2Go на русском НЕМИРКИН",
    "channel_url": "https://www.youtube.com/@nemirkin",
    "video_count": 1,
    "queries": [
      "как перестать всем угождать"
    ],
    "total_views": 20915,
    "sample_titles": [
      "How to Stop Being a People Pleaser"
    ]
  },
  {
    "channel_name": "SJBody",
    "channel_url": "https://www.youtube.com/@Sjbody",
    "video_count": 1,
    "queries": [
      "как научиться говорить нет"
    ],
    "total_views": 19743,
    "sample_titles": [
      "🔥 КАК НАУЧИТЬСЯ ГОВОРИТЬ НЕТ?"
    ]
  },
  {
    "channel_name": "Луиза, че делать ?!",
    "channel_url": "https://www.youtube.com/@Луизачеделать",
    "video_count": 1,
    "queries": [
      "самосаботаж"
    ],
    "total_views": 16280,
    "sample_titles": [
      "3 REASONS FOR SELF-SABOTAGE. Find Yours!"
    ]
  },
  {
    "channel_name": "Психолог Наталья Жукова",
    "channel_url": "https://www.youtube.com/@zhukova.natalia",
    "video_count": 1,
    "queries": [
      "токсичные отношения"
    ],
    "total_views": 16101,
    "sample_titles": [
      "The Main Signs of a TOXIC Relationship #psychology #manipulation"
    ]
  },
  {
    "channel_name": "CBT Clinic",
    "channel_url": "https://www.youtube.com/@CBTClinic",
    "video_count": 1,
    "queries": [
      "социальная тревога"
    ],
    "total_views": 15309,
    "sample_titles": [
      "СОЦИАЛЬНАЯ ТРЕВОЖНОСТЬ | Что это такое и как с ней бороться?"
    ]
  },
  {
    "channel_name": "Лысый Кактус",
    "channel_url": "https://www.youtube.com/@lysakyt",
    "video_count": 1,
    "queries": [
      "токсичные отношения"
    ],
    "total_views": 15288,
    "sample_titles": [
      "Signs of a Toxic Relationship"
    ]
  },
  {
    "channel_name": "Психолог Online",
    "channel_url": "https://www.youtube.com/@Psiholog-on-line",
    "video_count": 1,
    "queries": [
      "социофобия"
    ],
    "total_views": 13516,
    "sample_titles": [
      "КАК ИЗБАВИТЬСЯ ОТ СОЦИОФОБИИ: Честный Разговор"
    ]
  },
  {
    "channel_name": "Центр Когнитивной Терапии",
    "channel_url": "https://www.youtube.com/@selfhelp_info",
    "video_count": 1,
    "queries": [
      "социальная тревожность"
    ],
    "total_views": 12248,
    "sample_titles": [
      "Социальная тревожность. Видео 1. Что это такое?"
    ]
  },
  {
    "channel_name": "Константин Потапов",
    "channel_url": "https://www.youtube.com/@konstantinpotapovvpotoke",
    "video_count": 1,
    "queries": [
      "личные границы"
    ],
    "total_views": 10102,
    "sample_titles": [
      "КАК Я ЗАЩИТИЛ ЛИЧНЫЕ ГРАНИЦЫ - Пошаговый гайд - ПОЛУДЕННЫЙ ПОДКАСТ - Константин Потапов"
    ]
  },
  {
    "channel_name": "KSENIA AGEEVA: Career, Values & Brand",
    "channel_url": "https://www.youtube.com/@KseniAgeeva",
    "video_count": 1,
    "queries": [
      "самосаботаж"
    ],
    "total_views": 8975,
    "sample_titles": [
      "Самосаботаж | 100 КАРЬЕРНЫХ ОТВЕТОВ #40"
    ]
  },
  {
    "channel_name": "Психолог Татьяна Чувильчикова. «Не могу молчать!»",
    "channel_url": "https://www.youtube.com/@TChuvilchikova",
    "video_count": 1,
    "queries": [
      "как перестать всем угождать"
    ],
    "total_views": 8962,
    "sample_titles": [
      "GOOD for everyone? How to stop pleasing. A PSYCHOLOGIST'S recipe. #psychologist #maturity #bounda..."
    ]
  },
  {
    "channel_name": "Клиника Доктор САН",
    "channel_url": "https://www.youtube.com/@doctorsan",
    "video_count": 1,
    "queries": [
      "социальная тревога"
    ],
    "total_views": 8426,
    "sample_titles": [
      "Социальное тревожное расстройство: ✅ как подобрать метод лечения социофобии"
    ]
  },
  {
    "channel_name": "Алёна Булышева",
    "channel_url": "https://www.youtube.com/@alyona_bulysheva",
    "video_count": 1,
    "queries": [
      "самосаботаж"
    ],
    "total_views": 7814,
    "sample_titles": [
      "Самосаботаж: самый эффективный алгоритм выхода"
    ]
  },
  {
    "channel_name": "Сила. Свобода. Успех.",
    "channel_url": "https://www.youtube.com/@Mind.strategy",
    "video_count": 1,
    "queries": [
      "самосаботаж"
    ],
    "total_views": 6364,
    "sample_titles": [
      "How I Destroyed Self-Sabotage | The Powerful Practice That Changed My Life | Freedom Is the Highe..."
    ]
  },
  {
    "channel_name": "Sunnat Shukhratov",
    "channel_url": "https://www.youtube.com/@sunnatshukhratov",
    "video_count": 1,
    "queries": [
      "как научиться говорить нет"
    ],
    "total_views": 4950,
    "sample_titles": [
      "Как говорить НЕТ"
    ]
  },
  {
    "channel_name": "Евгений Мосеев психотерапевт",
    "channel_url": "https://www.youtube.com/@evgenij_moseev",
    "video_count": 1,
    "queries": [
      "токсичные отношения"
    ],
    "total_views": 4382,
    "sample_titles": [
      "Топ 6 признаков токсичных отношений | Психология отношений"
    ]
  },
  {
    "channel_name": "Лилия Левицкая ПСИХОЛОГ",
    "channel_url": "https://www.youtube.com/@liliya_levitskaya_psicholog",
    "video_count": 1,
    "queries": [
      "социальная тревога"
    ],
    "total_views": 3210,
    "sample_titles": [
      "ОДИНОЧЕСТВО, СОЦИАЛЬНАЯ ТРЕВОГА : САМООЦЕНКА ЧАСТЬ 6"
    ]
  }
]
