{
  "fetched_at": "2026-06-05T17:43:34+00:00",
  "collected_at": "2026-06-05T17:43:34+00:00",
  "video_id": "8592hR1PAcU",
  "video_url": "https://www.youtube.com/watch?v=8592hR1PAcU",
  "title": "Научиться говорить нет",
  "channel_name": "Тренер мотиватор Ирина Ковалева",
  "channel_url": "https://www.youtube.com/@ТренермотиваторИринаКовалева",
  "comments_count": 544,
  "thread_roots_count": 300,
  "reply_rows_count": 244,
  "sort_modes": [
    "top",
    "new"
  ],
  "per_sort_counts": {
    "top": 544,
    "new": 0
  },
  "status": "ok",
  "errors": {
    "new": "Command '['/Library/Frameworks/Python.framework/Versions/3.14/bin/yt-dlp', '--skip-download', '--write-info-json', '--write-comments', '--extractor-args', 'youtube:comment_sort=new', '-o', '/var/folders/34/8xxz40m55xj6dgc6nz8zvqj00000gn/T/yt-comments-r_9nvff7/%(id)s.%(ext)s', 'https://www.youtube.com/watch?v=8592hR1PAcU']' timed out after 40.0 seconds"
  },
  "source": "yt_dlp_comments"
}
